LICENSE.txt
README.md
setup.cfg
setup.py
yolovxx/__init__.py
yolovxx.egg-info/PKG-INFO
yolovxx.egg-info/SOURCES.txt
yolovxx.egg-info/dependency_links.txt
yolovxx.egg-info/requires.txt
yolovxx.egg-info/top_level.txt
yolovxx/yolov5/get_map.py
yolovxx/yolov5/kmeans_for_anchors.py
yolovxx/yolov5/predict.py
yolovxx/yolov5/summary.py
yolovxx/yolov5/train.py
yolovxx/yolov5/train__.py
yolovxx/yolov5/voc_annotation.py
yolovxx/yolov5/yolo.py
yolovxx/yolov5/nets/CSPdarknet.py
yolovxx/yolov5/nets/__init__.py
yolovxx/yolov5/nets/yolo.py
yolovxx/yolov5/nets/yolo_training.py
yolovxx/yolov5/utils/__init__.py
yolovxx/yolov5/utils/callbacks.py
yolovxx/yolov5/utils/dataloader.py
yolovxx/yolov5/utils/generate_classes.py
yolovxx/yolov5/utils/utils.py
yolovxx/yolov5/utils/utils_bbox.py
yolovxx/yolov5/utils/utils_fit.py
yolovxx/yolov5/utils/utils_map.py
yolovxx/yolov7/__init__.py
yolovxx/yolov7/get_map.py
yolovxx/yolov7/kmeans_for_anchors.py
yolovxx/yolov7/train.py
yolovxx/yolov7/voc_annotation.py
yolovxx/yolov7/yolo.py
yolovxx/yolov7/nets/__init__.py
yolovxx/yolov7/nets/backbone.py
yolovxx/yolov7/nets/yolo.py
yolovxx/yolov7/nets/yolo_training.py
yolovxx/yolov7/utils/__init__.py
yolovxx/yolov7/utils/callbacks.py
yolovxx/yolov7/utils/dataloader.py
yolovxx/yolov7/utils/generate_classes.py
yolovxx/yolov7/utils/utils.py
yolovxx/yolov7/utils/utils_bbox.py
yolovxx/yolov7/utils/utils_fit.py
yolovxx/yolov7/utils/utils_map.py
yolovxx/yolox/train.py
yolovxx/yolox/voc_annotation.py
yolovxx/yolox/yolo.py
yolovxx/yolox/nets/__init__.py
yolovxx/yolox/nets/darknet.py
yolovxx/yolox/nets/yolo.py
yolovxx/yolox/nets/yolo_training.py
yolovxx/yolox/utils/__init__.py
yolovxx/yolox/utils/callbacks.py
yolovxx/yolox/utils/dataloader.py
yolovxx/yolox/utils/generate_classes.py
yolovxx/yolox/utils/utils.py
yolovxx/yolox/utils/utils_bbox.py
yolovxx/yolox/utils/utils_fit.py
yolovxx/yolox/utils/utils_map.py