Metadata-Version: 2.1
Name: yolovxx
Version: 1.9.8
Summary: run all yolo detectors (training and inference)
Home-page: https://hoolme.ai
Download-URL: https://github.com/user/reponame/archive/v_01.tar.gz
Author: NasAir
Author-email: me@domain.com
License: MIT
Keywords: SOME,MEANINGFULL,KEYWORDS
Classifier: Development Status :: 3 - Alpha
Classifier: Intended Audience :: Developers
Classifier: Topic :: Software Development :: Build Tools
Classifier: License :: OSI Approved :: MIT License
Classifier: Programming Language :: Python :: 3.6
Classifier: Programming Language :: Python :: 3.7
Classifier: Programming Language :: Python :: 3.8
Classifier: Programming Language :: Python :: 3.9
License-File: LICENSE.txt
